{
  "frutas": [
    "manzana",
    "banana",
    "naranja",
    "uva",
    "kiwi",
    "fresa",
    "pera",
    "sandía",
    "cereza",
    "mango",
    "melón",
    "piña",
    "limón",
    "ciruela",
    "pomelo",
    "papaya",
    "guayaba",
    "frambuesa",
    "granada",
    "higo",
    "maracuyá",
    "coco",
    "mandarina",
    "zarzamora",
    "pomelo",
    "nectarina",
    "durazno",
    "membrillo",
    "chirimoya",
    "litchi",
    "tamarindo",
    "kiwano",
    "caqui",
    "rábanito",
    "carambola",
    "níspero",
    "mora",
    "jaca",
    "zarza",
    "café",
    "almendra",
    "dátil",
    "cacao"
  ],
  "capitales": [
    "Tirana",
    "Berlín",
    "Viena",
    "Bruselas",
    "Minsk",
    "Sarajevo",
    "Sofía",
    "Praga",
    "Zagreb",
    "Copenhague",
    "Bratislava",
    "Liubliana",
    "Madrid",
    "Tallin",
    "Helsinki",
    "París",
    "Atenas",
    "Budapest",
    "Dublín",
    "Reikiavik",
    "Roma",
    "Riga",
    "Vaduz",
    "Vilna",
    "Luxemburgo",
    "Skopie",
    "Chisinau",
    "Mónaco",
    "Oslo",
    "Ámsterdam",
    "Varsovia",
    "Lisboa",
    "Londres",
    "Bucarest",
    "Moscú",
    "Estocolmo",
    "Berna",
    "Ankara",
    "Kiev",
    "Belgrado",
    "Nassau",
    "Bridgetown",
    "Belmopán",
    "Sucre",
    "Brasilia",
    "Ottawa",
    "Bogotá",
    "Roseau",
    "Quito",
    "Georgetown",
    "Tegucigalpa",
    "Kingston",
    "Managua",
    "Panamá",
    "Asunción",
    "Lima",
    "Basseterre",
    "Kingstown",
    "Castries",
    "Paramaribo",
    "Montevideo",
    "Caracas",
    "Kabul",
    "Riad",
    "Ereván",
    "Bakú",
    "Manama",
    "Daca",
    "Timbu",
    "Pekín",
    "Nicosia",
    "Pyongyang",
    "Seúl",
    "Manila",
    "Tiflis",
    "Yakarta",
    "Bagdad",
    "Teherán",
    "Jerusalén",
    "Tokio",
    "Amán",
    "Astana",
    "Biskek",
    "Kuwait",
    "Vientián",
    "Beirut",
    "Malé",
    "Yangón",
    "Katmandú",
    "Mascate",
    "Islamabad",
    "Doha",
    "Singapur",
    "Damasco",
    "Colombo",
    "Bangkok",
    "Dusambé",
    "Asjabad",
    "Taskent",
    "Hanói",
    "Sana",
    "Dili",
    "Luanda",
    "Argel",
    "Gaborone",
    "Uagadugú",
    "Buyumbura",
    "Praia",
    "Yaundé",
    "Bangui",
    "Yamena",
    "Moroni",
    "Brazaville",
    "Kinshasa",
    "Yamusukro",
    "Yibuti",
    "Asmara",
    "Libreville",
    "Banjul",
    "Acra",
    "Bisáu",
    "Conakri",
    "Malabo",
    "Nairobi",
    "Maseru",
    "Monrovia",
    "Trípoli",
    "Antananarivo",
    "Bamako",
    "Rabat",
    "Nuakchot",
    "Maputo",
    "Windhoek",
    "Niamey",
    "Abuya",
    "Kigali",
    "Dakar",
    "Victoria",
    "Freetown",
    "Mogadiscio",
    "Pretoria",
    "Jartum",
    "Mbabane",
    "Dodoma",
    "Lomé",
    "Túnez",
    "Kampala",
    "Lusaka",
    "Harare",
    "Suva",
    "Bairiki",
    "Majuro",
    "Palikir",
    "Yaren",
    "Wellington",
    "Koror",
    "Honiara",
    "Apia",
    "Fongafale",
    "Avarua"
  ],
  "animales": [
    "águila",
    "ardilla",
    "armadillo",
    "avestruz",
    "ballena",
    "búho",
    "burro",
    "caballo",
    "cabra",
    "caimán",
    "calamar",
    "cangrejo",
    "castor",
    "ciervo",
    "cocodrilo",
    "cóndor",
    "conejo",
    "culebra",
    "delfín",
    "elefante",
    "foca",
    "gacela",
    "ganso",
    "gato",
    "gaviota",
    "gorila",
    "grulla",
    "halcón",
    "hipopótamo",
    "iguana",
    "jirafa",
    "lemur",
    "león",
    "loro",
    "mantis",
    "mapache",
    "marmota",
    "medusa",
    "murciélago",
    "narval",
    "nutria",
    "ornitorrinco",
    "paloma",
    "pantera",
    "pavo",
    "pelícano",
    "perro",
    "pinguino",
    "puma",
    "serpiente",
    "tejón",
    "tiburón",
    "tigre",
    "tortuga",
    "trucha",
    "tucán",
    "unicornio",
    "vaca",
    "yaguareté",
    "cebra",
    "zorro"
  ],
  "trabajos": [
    "médico",
    "abogado",
    "ingeniero",
    "arquitecto",
    "profesor",
    "enfermero",
    "contador",
    "electricista",
    "plomero",
    "programador",
    "policía",
    "bombero",
    "piloto",
    "astronauta",
    "científico",
    "actor",
    "músico",
    "escritor",
    "diseñador",
    "veterinario",
    "psicólogo",
    "chef",
    "camarero",
    "periodista",
    "economista",
    "geólogo",
    "químico",
    "fotógrafo",
    "carpintero",
    "fontanero",
    "mecánico",
    "cirujano",
    "farmacéutico",
    "cineasta",
    "cantante",
    "pintor",
    "biólogo",
    "matemático",
    "arqueólogo",
    "atleta",
    "físico",
    "antropólogo",
    "psiquiatra",
    "dentista",
    "agricultor",
    "gerente",
    "conductor",
    "entrenador",
    "maestro",
    "analista",
    "tecnólogo",
    "narrador",
    "orador",
    "investigador",
    "consultor"
  ],
  "peliculas": [
    "Titanic",
    "El Padrino",
    "La La Land",
    "Matrix",
    "Whiplash",
    "El Señor de los Anillos",
    "Star Wars",
    "ET el Extraterrestre",
    "Forrest Gump",
    "Harry Potter y la Piedra Filosofal",
    "Gladiador",
    "Jurassic Park",
    "Pulp Fiction",
    "Avatar",
    "Los Intocables",
    "La Lista de Schindler",
    "Resacón en Las Vegas",
    "Misión Imposible",
    "Mad Max Fury Road",
    "Blade Runner",
    "El Laberinto del Fauno",
    "Narnia",
    "Moulin Rouge",
    "American Beauty",
    "El Gran Gatsby",
    "La Bella y la Bestia",
    "El Silencio de los Inocentes",
    "La Sirenita",
    "El Rey León",
    "Bailando con Lobos",
    "Náufrago",
    "El Lobo de Wall Street",
    "Inception",
    "Forrest Gump",
    "Fight Club",
    "La Bella y la Bestia",
    "La Sirenita",
    "Aladdin",
    "Toy Story",
    "Buscando a Nemo",
    "Ratatouille",
    "Wall E",
    "Enredados",
    "Frozen",
    "Moana",
    "Coco",
    "Zootopia",
    "Ralph el Demoledor",
    "Soul",
    "Luca",
    "Raya y el último dragón",
    "Encanto",
    "Los Increíbles",
    "Cars",
    "Valiente",
    "El Libro de la Selva",
    "La Dama y el Vagabundo",
    "Mulan",
    "Blancanieves y los Siete Enanitos",
    "Cenicienta",
    "La Bella Durmiente",
    "Pinocho",
    "Peter Pan",
    "Alicia en el País de las Maravillas",
    "El Libro de la Selva",
    "Robin Hood",
    "Bernardo y Bianca",
    "La Cenicienta",
    "La Bella Durmiente",
    "La Espada en la Piedra",
    "Ratónpolis",
    "Tiana y el Sapo",
    "Enredados",
    "Aviones",
    "Intensa Mente",
    "Piratas del Caribe"
  ],
  "superheroes": [
    "Hombre Araña",
    "Superman",
    "Batman",
    "Mujer Maravilla",
    "Flash",
    "Aquaman",
    "Linterna Verde",
    "Hombre de Hierro",
    "Capitán América",
    "Thor",
    "Hulk",
    "Black Widow",
    "Black Panther",
    "Doctor Strange",
    "Antman",
    "Wolverine",
    "Deadpool",
    "Capitana Marvel",
    "Ojo de Halcón",
    "Bruja Escarlata",
    "Falcon",
    "Visión",
    "Doctor Doom",
    "Flecha Verde",
    "Supergirl",
    "Batwoman",
    "Nightwing",
    "Robin",
    "Daredevil",
    "Luke Cage",
    "Jessica Jones",
    "Puño de Hierro",
    "Blue Beetle",
    "Cyborg",
    "Starfire",
    "Raven",
    "Chico Bestia",
    "Cíclope",
    "Coloso",
    "Magneto",
    "Profesor X",
    "Silver Surfer",
    "Deadshot",
    "Harley Quinn",
    "Duende Verde",
    "Doctor Octopus",
    "Hombre de Arena",
    "Venom",
    "Carnage",
    "El Joker",
    "Acertijo",
    "Catwoman",
    "Dos Caras",
    "Bane",
    "Hiedra Venenosa"
  ]
}
